gw_dsl_parser/__init__.py
gw_dsl_parser/core.py
gw_dsl_parser/dsl_parser.wasm
gw_dsl_parser-0.1.43.dist-info/METADATA
gw_dsl_parser-0.1.43.dist-info/WHEEL
gw_dsl_parser-0.1.43.dist-info/licenses/LICENSE
gw_dsl_parser-0.1.43.dist-info/RECORD
