Metadata-Version: 2.1
Name: gw_dsl_parser
Version: 0.1.43
Summary: gw_dsl_parser: Convert your graphic-walker workflow to sql
Project-URL: homepage, https://github.com/Kanaries/gw-dsl-parser-py
Project-URL: repository, https://github.com/Kanaries/gw-dsl-parser-py
Author-email: kanaries <support@kanaries.net>
License-File: LICENSE
Keywords: graphic-walker,pygwalker
Classifier: License :: OSI Approved :: Apache Software License
Classifier: Programming Language :: Python :: 3
Requires-Python: >=3.6
Requires-Dist: wasmtime==12.0.0
Provides-Extra: dev
Requires-Dist: build; extra == 'dev'
Requires-Dist: pytest; extra == 'dev'
Requires-Dist: twine; extra == 'dev'
